mosstool/__init__.py
mosstool/map/__init__.py
mosstool/map/_map_util/aois/__init__.py
mosstool/map/_map_util/aois/append_aois_matcher.py
mosstool/map/_map_util/aois/convert_aoi_poi.py
mosstool/map/_map_util/aois/match_aoi_pop.py
mosstool/map/_map_util/aois/reuse_aois_matchers.py
mosstool/map/_map_util/aois/utils.py
mosstool/map/_map_util/const.py
mosstool/map/_map_util/format_checker.py
mosstool/map/_map_util/junctions/__init__.py
mosstool/map/_map_util/junctions/gen_traffic_light.py
mosstool/map/_map_util/junctions/utils.py
mosstool/map/_map_util/osm_const.py
mosstool/map/_util/__init__.py
mosstool/map/_util/angle.py
mosstool/map/_util/bezier.py
mosstool/map/_util/line.py
mosstool/map/builder/__init__.py
mosstool/map/builder/builder.py
mosstool/map/gmns/__init__.py
mosstool/map/gmns/convertor.py
mosstool/map/osm/__init__.py
mosstool/map/osm/_motif.py
mosstool/map/osm/_wayutil.py
mosstool/map/osm/building.py
mosstool/map/osm/point_of_interest.py
mosstool/map/osm/roadnet.py
mosstool/map/public_transport/__init__.py
mosstool/map/public_transport/get_bus.py
mosstool/map/public_transport/get_subway.py
mosstool/map/public_transport/get_transitland.py
mosstool/map/public_transport/gtfs_converter.py
mosstool/map/public_transport/public_transport_post.py
mosstool/map/sumo/__init__.py
mosstool/map/sumo/map.py
mosstool/trip/__init__.py
mosstool/trip/generator/AIGC.py
mosstool/trip/generator/__init__.py
mosstool/trip/generator/_util/const.py
mosstool/trip/generator/_util/utils.py
mosstool/trip/generator/generate_from_od.py
mosstool/trip/generator/gravity.py
mosstool/trip/generator/random.py
mosstool/trip/generator/template.py
mosstool/trip/gmns/__init__.py
mosstool/trip/gmns/sta.py
mosstool/trip/route/__init__.py
mosstool/trip/route/client.py
mosstool/trip/route/preroute.py
mosstool/trip/sumo/__init__.py
mosstool/trip/sumo/route.py
mosstool/type/__init__.py
mosstool/util/__init__.py
mosstool/util/color.py
mosstool/util/format_converter.py
mosstool/util/geo_match_pop.py
mosstool-1.3.20.dist-info/METADATA
mosstool-1.3.20.dist-info/WHEEL
mosstool-1.3.20.dist-info/RECORD
